Metadata-Version: 2.1
Name: odoo12-addon-mrp-multi-level-estimate
Version: 12.0.1.1.0
Summary: Allows to consider demand estimates using MRP multi level.
Home-page: https://github.com/OCA/manufacture
Author: ForgeFlow, Odoo Community Association (OCA)
Author-email: support@odoo-community.org
License: AGPL-3
Platform: UNKNOWN
Classifier: Programming Language :: Python
Classifier: Framework :: Odoo
Classifier: License :: OSI Approved :: GNU Affero General Public License v3
Classifier: Development Status :: 4 - Beta
Requires-Python: >=3.5
Requires-Dist: odoo12-addon-mrp-multi-level
Requires-Dist: odoo12-addon-stock-demand-estimate-matrix
Requires-Dist: odoo (<12.1dev,>=12.0a)
